DiscordTos/__init__.py
DiscordTos-0.0.1.dist-info/LICENSE
DiscordTos-0.0.1.dist-info/METADATA
DiscordTos-0.0.1.dist-info/WHEEL
DiscordTos-0.0.1.dist-info/top_level.txt
DiscordTos-0.0.1.dist-info/RECORD
